ibm_dfo_sdk/__init__.py
ibm_dfo_sdk/common.py
ibm_dfo_sdk/extended_api.py
ibm_dfo_sdk/get_service.py
ibm_dfo_sdk/ibm_data_fabric_orchestrator_v1.py
ibm_dfo_sdk/ibm_data_fabric_orchestrator_v1_dummy.py
ibm_dfo_sdk/token_auth_handler.py
ibm_dfo_sdk/version.py
ibm_dfo_sdk-0.0.11.dist-info/LICENSE
ibm_dfo_sdk-0.0.11.dist-info/METADATA
ibm_dfo_sdk-0.0.11.dist-info/WHEEL
ibm_dfo_sdk-0.0.11.dist-info/top_level.txt
ibm_dfo_sdk-0.0.11.dist-info/zip-safe
ibm_dfo_sdk-0.0.11.dist-info/RECORD
