Metadata-Version: 2.1
Name: ibm-dfo-sdk
Version: 0.0.11
Summary: IBM Data Fabric Orchestrator python SDK
Home-page: https://github.com/IBM/dfo-python-sdk.git
Author: IBM
Author-email: pugangxa@cn.ibm.com
License: Apache 2.0
Keywords: ibm_dfo_sdk
Classifier: Programming Language :: Python
Classifier: Programming Language :: Python :: 3
Classifier: Programming Language :: Python :: 3.7
Classifier: Programming Language :: Python :: 3.8
Classifier: Programming Language :: Python :: 3.9
Classifier: Programming Language :: Python :: 3.10
Classifier: Development Status :: 4 - Beta
Classifier: Intended Audience :: Developers
Classifier: License :: OSI Approved :: Apache Software License
Classifier: Operating System :: OS Independent
Classifier: Topic :: Software Development :: Libraries :: Python Modules
Classifier: Topic :: Software Development :: Libraries :: Application Frameworks
License-File: LICENSE
Requires-Dist: requests (<3.0.0,>=2.26.0)
Requires-Dist: urllib3 (<2.0.0,>=1.26.0)
Requires-Dist: python-dateutil (<3.0.0,>=2.5.3)
Requires-Dist: ibm-cloud-sdk-core (<4.0.0,>=3.10.0)
Requires-Dist: pyarrow (>=8.0.0)
